pyramid_cas/__init__.py
pyramid_cas/services.py
pyramid_cas/tests.py
pyramid_cas/views.py
pyramid_cas/templates/mytemplate.pt
pyramid_cas-0.4.dist-info/LICENSE
pyramid_cas-0.4.dist-info/METADATA
pyramid_cas-0.4.dist-info/WHEEL
pyramid_cas-0.4.dist-info/entry_points.txt
pyramid_cas-0.4.dist-info/top_level.txt
pyramid_cas-0.4.dist-info/RECORD
