Metadata-Version: 2.1
Name: pyramid-cas
Version: 0.4
Summary: A CAS client for use with the Pyramid web framework
Home-page: https://github.com/ryanfox/pyramid_cas
Author: Ryan Fox
Author-email: ryan@foxrow.com
License: Apache license
Keywords: web pyramid pylons cas authentication
Classifier: Programming Language :: Python
Classifier: Framework :: Pyramid
Classifier: Topic :: Internet :: WWW/HTTP
Classifier: Topic :: Internet :: WWW/HTTP :: WSGI :: Application
Classifier: License :: OSI Approved :: Apache Software License
License-File: LICENSE
Requires-Dist: pyramid
Requires-Dist: SQLAlchemy
Requires-Dist: transaction
Requires-Dist: pyramid-tm
Requires-Dist: pyramid-debugtoolbar
Requires-Dist: zope.sqlalchemy
